<?xml version="1.0" encoding="utf-8" ?><dwsync><file name="1.png" server="classweb.soc.northwestern.edu//var/www/html/jenniferhutson2021/" local="3634424512" remote="3634424589" Dst="-1" /><file name="10.png" server="classweb.soc.northwestern.edu//var/www/html/jenniferhutson2021/" local="3634425718" remote="3634426310" Dst="-1" /><file name="11.png" server="classweb.soc.northwestern.edu//var/www/html/jenniferhutson2021/" local="3634425751" remote="3634426310" Dst="-1" /><file name="12.png" server="classweb.soc.northwestern.edu//var/www/html/jenniferhutson2021/" local="3634425767" remote="3634426310" Dst="-1" /><file name="13.png" server="classweb.soc.northwestern.edu//var/www/html/jenniferhutson2021/" local="3634425784" remote="3634426310" Dst="-1" /><file name="14.png" server="classweb.soc.northwestern.edu//var/www/html/jenniferhutson2021/" local="3634425800" remote="3634426310" Dst="-1" /><file name="2.png" server="classweb.soc.northwestern.edu//var/www/html/jenniferhutson2021/" local="3634425543" remote="3634426310" Dst="-1" /><file name="3.png" server="classweb.soc.northwestern.edu//var/www/html/jenniferhutson2021/" local="3634425588" remote="3634426310" Dst="-1" /><file name="4.png" server="classweb.soc.northwestern.edu//var/www/html/jenniferhutson2021/" local="3634425609" remote="3634426310" Dst="-1" /><file name="5.png" server="classweb.soc.northwestern.edu//var/www/html/jenniferhutson2021/" local="3634425628" remote="3634426310" Dst="-1" /><file name="6.png" server="classweb.soc.northwestern.edu//var/www/html/jenniferhutson2021/" local="3634425646" remote="3634426310" Dst="-1" /><file name="7.png" server="classweb.soc.northwestern.edu//var/www/html/jenniferhutson2021/" local="3634425662" remote="3634426310" Dst="-1" /><file name="8.png" server="classweb.soc.northwestern.edu//var/www/html/jenniferhutson2021/" local="3634425679" remote="3634426310" Dst="-1" /><file name="9.png" server="classweb.soc.northwestern.edu//var/www/html/jenniferhutson2021/" local="3634425695" remote="3634426310" Dst="-1" /></dwsync>